inni/__init__.py
inni/cli.py
inni/config.py
inni/loader.py
inni/modules/__init__.py
inni/modules/base.py
inni/modules/bitrix.py
inni/modules/dummy.py
inni/modules/email.py
inni/modules/jira.py
inni/modules/runner.py
inni/modules/skype.py
inni/template.py
inni-0.5.2.dist-info/LICENSE
inni-0.5.2.dist-info/METADATA
inni-0.5.2.dist-info/WHEEL
inni-0.5.2.dist-info/entry_points.txt
inni-0.5.2.dist-info/RECORD
