Metadata-Version: 2.1
Name: inni
Version: 0.5.2
Summary: Modular system to perform tasks surrounding log-in and log-out.
Home-page: https://gitlab.com/ceda_ei/inni
License: GPL-3.0
Author: Ceda EI
Author-email: ceda_ei@webionite.com
Requires-Python: >=3.11,<4.0
Classifier: License :: OSI Approved :: GNU General Public License v3 (GPLv3)
Classifier: Programming Language :: Python :: 3
Classifier: Programming Language :: Python :: 3.11
Classifier: Programming Language :: Python :: 3.12
Requires-Dist: click (>=8.1.7,<9.0.0)
Requires-Dist: jinja2 (>=3.1.3,<4.0.0)
Requires-Dist: jira (>=3.8.0,<4.0.0)
Requires-Dist: playwright (>=1.43.0,<2.0.0)
Requires-Dist: prompt-toolkit (>=3.0.43,<4.0.0)
Requires-Dist: psutil (>=5.9.8,<6.0.0)
Requires-Dist: rich (>=13.7.1,<14.0.0)
Requires-Dist: skpy (>=0.10.6,<0.11.0)
Project-URL: Repository, https://gitlab.com/ceda_ei/inni
